CHANGELOG.md
LICENSE
MANIFEST.in
README.md
TODO.md
requirements.txt
setup.py
flask_kits/__init__.py
flask_kits.egg-info/PKG-INFO
flask_kits.egg-info/SOURCES.txt
flask_kits.egg-info/dependency_links.txt
flask_kits.egg-info/requires.txt
flask_kits.egg-info/top_level.txt
flask_kits/account/__init__.py
flask_kits/common/__init__.py
flask_kits/common/code.py
flask_kits/decorators/__init__.py
flask_kits/decorators/permission.py
flask_kits/exceptions/__init__.py
flask_kits/restful/__init__.py
flask_kits/restful/filter.py
flask_kits/restful/meta.py
flask_kits/restful/pagination.py
flask_kits/restful/parser.py
flask_kits/restful/resource.py
flask_kits/restful/serializer.py
flask_kits/restful/swagger.py
flask_kits/restful/entity/__init__.py
flask_kits/restful/entity/common.py
flask_kits/restful/entity/pagination.py
flask_kits/restful/entity/response.py
flask_kits/restful/entity/validator.py
flask_kits/restful/fields/__init__.py
flask_kits/restful/fields/date.py
flask_kits/restful/fields/status.py
flask_kits/routing/__init__.py
flask_kits/sms/__init__.py
flask_kits/ui/__init__.py
flask_kits/ui/menu.py
flask_kits/utils/__init__.py
flask_kits/utils/bunch.py
flask_kits/utils/pay.py
flask_kits/utils/rand.py
flask_kits/utils/signature.py
flask_kits/utils/template_message.py
flask_kits/utils/util.py
flask_kits/utils/validation.py
test/__init__.py
test/test_flask_kits.py
test/test_flask_restful_validator.py